module/__init__.py
module/ascii_art.txt
module/fakehacker.txt
module/walnutmod.py
walnutmod-0.2.dist-info/METADATA
walnutmod-0.2.dist-info/WHEEL
walnutmod-0.2.dist-info/top_level.txt
walnutmod-0.2.dist-info/RECORD
